dockercomposeexample.py
dockercomposeexample-0.2.1.dist-info/LICENSE.txt
dockercomposeexample-0.2.1.dist-info/METADATA
dockercomposeexample-0.2.1.dist-info/WHEEL
dockercomposeexample-0.2.1.dist-info/RECORD
