Metadata-Version: 2.3
Name: DockerComposeExample
Version: 0.2.1
Summary: Docker Compose Example
License: MIT
Author: Hendrik du Toit
Author-email: hendrik@brightedge.co.za
Maintainer: Hendrik du Toit
Maintainer-email: hendrikdt@citiqprepaid.co.za
Requires-Python: >=3.10
Classifier: Development Status :: 4 - Beta
Classifier: Intended Audience :: Developers
Classifier: Intended Audience :: Information Technology
Classifier: Intended Audience :: System Administrators
Classifier: License :: OSI Approved :: MIT License
Classifier: Topic :: Software Development :: Libraries :: Python Modules
Classifier: Topic :: System :: Archiving :: Packaging
Classifier: Programming Language :: Python :: 3.10
Classifier: Programming Language :: Python :: 3.11
Classifier: Programming Language :: Python :: 3.12
Classifier: Programming Language :: Python :: 3.13
Requires-Dist: flask (>=3.1.0,<4.0.0)
Requires-Dist: redis (>=5.2.1,<6.0.0)
Project-URL: Changelog, https://github.com/hendrikdutoit/dockercomposeexample/blob/enhancement/master/ReleaseNotes.md
Project-URL: Homepage, https://github.com/hendrikdutoit/dockercomposeexample
Project-URL: Issues, https://github.com/hendrikdutoit/dockercomposeexample/issues
Project-URL: Repository, https://github.com/hendrikdutoit/dockercomposeexample.git
